{
    "boxShadow": "none",
    "isVisibleDownload": false,
    "iconSVG": "/static/media/icon.db8a9cbd.svg",
    "topRow": 10,
    "isSortable": true,
    "onPageChange": "{{fetch_users_data.run()}}",
    "type": "TABLE_WIDGET",
    "animateLoading": true,
    "dynamicBindingPathList": [
        {"key": "tableData"},
        {"key": "totalRecordsCount"},
        {"key": "primaryColumns.id.computedValue"},
        {"key": "primaryColumns.gender.computedValue"},
        {"key": "primaryColumns.latitude.computedValue"},
        {"key": "primaryColumns.longitude.computedValue"},
        {"key": "primaryColumns.dob.computedValue"},
        {"key": "primaryColumns.phone.computedValue"},
        {"key": "primaryColumns.email.computedValue"},
        {"key": "primaryColumns.image.computedValue"},
        {"key": "primaryColumns.country.computedValue"},
        {"key": "primaryColumns.name.computedValue"},
        {"key": "accentColor"},
        {"key": "primaryColumns.created_at.computedValue"},
        {"key": "primaryColumns.updated_at.computedValue"}
    ],
    "leftColumn": 0,
    "delimiter": ",",
    "accentColor": "{{appsmith.theme.colors.primaryColor}}",
    "isVisibleFilters": false,
    "isVisible": true,
    "enableClientSideSearch": true,
    "version": 3,
    "totalRecordsCount": "{{fetch_users_count.data[0].count}}",
    "isLoading": false,
    "childStylesheet": {
        "button": {
            "boxShadow": "none",
            "borderRadius": "{{appsmith.theme.borderRadius.appBorderRadius}}",
            "buttonColor": "{{appsmith.theme.colors.primaryColor}}"
        },
        "iconButton": {
            "boxShadow": "none",
            "borderRadius": "{{appsmith.theme.borderRadius.appBorderRadius}}",
            "menuColor": "{{appsmith.theme.colors.primaryColor}}"
        },
        "menuButton": {
            "boxShadow": "none",
            "borderRadius": "{{appsmith.theme.borderRadius.appBorderRadius}}",
            "menuColor": "{{appsmith.theme.colors.primaryColor}}"
        }
    },
    "borderRadius": "0px",
    "columnSizeMap": {
        "task": 245,
        "step": 62,
        "status": 75
    },
    "widgetName": "Table1",
    "defaultPageSize": 0,
    "columnOrder": [
        "id",
        "gender",
        "latitude",
        "longitude",
        "dob",
        "phone",
        "email",
        "image",
        "country",
        "name",
        "created_at",
        "updated_at"
    ],
    "dynamicPropertyPathList": [{"key": "onPageChange"}],
    "displayName": "Table",
    "bottomRow": 58,
    "parentRowSpace": 10,
    "defaultSelectedRow": "0",
    "hideCard": false,
    "onPageSizeChange": "{{fetch_users_data.run()}}",
    "dynamicTriggerPathList": [
        {"key": "onPageChange"},
        {"key": "onPageSizeChange"}
    ],
    "primaryColumns": {
        "image": {
            "isCellVisible": true,
            "boxShadow": "none",
            "isDerived": false,
            "computedValue": "{{Table1.sanitizedTableData.map((currentRow) => ( currentRow.image))}}",
            "textSize": "0.875rem",
            "index": 7,
            "isVisible": true,
            "label": "image",
            "columnType": "text",
            "horizontalAlignment": "LEFT",
            "borderRadius": "0px",
            "width": 150,
            "enableFilter": true,
            "enableSort": true,
            "id": "image",
            "isDisabled": false,
            "verticalAlignment": "CENTER"
        },
        "country": {
            "isCellVisible": true,
            "boxShadow": "none",
            "isDerived": false,
            "computedValue": "{{Table1.sanitizedTableData.map((currentRow) => ( currentRow.country))}}",
            "textSize": "0.875rem",
            "index": 8,
            "isVisible": true,
            "label": "country",
            "columnType": "text",
            "horizontalAlignment": "LEFT",
            "borderRadius": "0px",
            "width": 150,
            "enableFilter": true,
            "enableSort": true,
            "id": "country",
            "isDisabled": false,
            "verticalAlignment": "CENTER"
        },
        "gender": {
            "isCellVisible": true,
            "boxShadow": "none",
            "isDerived": false,
            "computedValue": "{{Table1.sanitizedTableData.map((currentRow) => ( currentRow.gender))}}",
            "textSize": "0.875rem",
            "index": 1,
            "isVisible": true,
            "label": "gender",
            "columnType": "text",
            "horizontalAlignment": "LEFT",
            "borderRadius": "0px",
            "width": 150,
            "enableFilter": true,
            "enableSort": true,
            "id": "gender",
            "isDisabled": false,
            "verticalAlignment": "CENTER"
        },
        "updated_at": {
            "isCellVisible": true,
            "isDerived": false,
            "computedValue": "{{Table1.sanitizedTableData.map((currentRow) => ( currentRow.updated_at))}}",
            "textSize": "0.875rem",
            "index": 11,
            "isVisible": true,
            "label": "updated_at",
            "textColor": "",
            "columnType": "text",
            "horizontalAlignment": "LEFT",
            "width": 150,
            "enableFilter": true,
            "enableSort": true,
            "id": "updated_at",
            "isDisabled": false,
            "cellBackground": "",
            "verticalAlignment": "CENTER"
        },
        "phone": {
            "isCellVisible": true,
            "boxShadow": "none",
            "isDerived": false,
            "computedValue": "{{Table1.sanitizedTableData.map((currentRow) => ( currentRow.phone))}}",
            "textSize": "0.875rem",
            "index": 5,
            "isVisible": true,
            "label": "phone",
            "columnType": "text",
            "horizontalAlignment": "LEFT",
            "borderRadius": "0px",
            "width": 150,
            "enableFilter": true,
            "enableSort": true,
            "id": "phone",
            "isDisabled": false,
            "verticalAlignment": "CENTER"
        },
        "dob": {
            "isCellVisible": true,
            "boxShadow": "none",
            "isDerived": false,
            "computedValue": "{{Table1.sanitizedTableData.map((currentRow) => ( moment(currentRow.dob).format(\"MM/DD/yyyy\")))}}",
            "textSize": "0.875rem",
            "index": 4,
            "isVisible": true,
            "label": "dob",
            "columnType": "text",
            "horizontalAlignment": "LEFT",
            "borderRadius": "0px",
            "width": 150,
            "enableFilter": true,
            "enableSort": true,
            "id": "dob",
            "isDisabled": false,
            "verticalAlignment": "CENTER"
        },
        "latitude": {
            "isCellVisible": true,
            "boxShadow": "none",
            "isDerived": false,
            "computedValue": "{{Table1.sanitizedTableData.map((currentRow) => ( currentRow.latitude))}}",
            "textSize": "0.875rem",
            "index": 2,
            "isVisible": true,
            "label": "latitude",
            "columnType": "text",
            "horizontalAlignment": "LEFT",
            "borderRadius": "0px",
            "width": 150,
            "enableFilter": true,
            "enableSort": true,
            "id": "latitude",
            "isDisabled": false,
            "verticalAlignment": "CENTER"
        },
        "name": {
            "isCellVisible": true,
            "boxShadow": "none",
            "isDerived": false,
            "computedValue": "{{Table1.sanitizedTableData.map((currentRow) => ( currentRow.name))}}",
            "textSize": "0.875rem",
            "index": 9,
            "isVisible": true,
            "label": "name",
            "columnType": "text",
            "horizontalAlignment": "LEFT",
            "borderRadius": "0px",
            "width": 150,
            "enableFilter": true,
            "enableSort": true,
            "id": "name",
            "isDisabled": false,
            "verticalAlignment": "CENTER"
        },
        "created_at": {
            "isCellVisible": true,
            "isDerived": false,
            "computedValue": "{{Table1.sanitizedTableData.map((currentRow) => ( currentRow.created_at))}}",
            "textSize": "0.875rem",
            "index": 10,
            "isVisible": true,
            "label": "created_at",
            "textColor": "",
            "columnType": "text",
            "horizontalAlignment": "LEFT",
            "width": 150,
            "enableFilter": true,
            "enableSort": true,
            "id": "created_at",
            "isDisabled": false,
            "cellBackground": "",
            "verticalAlignment": "CENTER"
        },
        "id": {
            "isCellVisible": true,
            "boxShadow": "none",
            "isDerived": false,
            "computedValue": "{{Table1.sanitizedTableData.map((currentRow) => ( currentRow.id))}}",
            "textSize": "0.875rem",
            "index": 0,
            "isVisible": true,
            "label": "id",
            "columnType": "text",
            "horizontalAlignment": "LEFT",
            "borderRadius": "0px",
            "width": 150,
            "enableFilter": true,
            "enableSort": true,
            "id": "id",
            "isDisabled": false,
            "verticalAlignment": "CENTER"
        },
        "email": {
            "isCellVisible": true,
            "boxShadow": "none",
            "isDerived": false,
            "computedValue": "{{Table1.sanitizedTableData.map((currentRow) => ( currentRow.email))}}",
            "textSize": "0.875rem",
            "index": 6,
            "isVisible": true,
            "label": "email",
            "columnType": "text",
            "horizontalAlignment": "LEFT",
            "borderRadius": "0px",
            "width": 150,
            "enableFilter": true,
            "enableSort": true,
            "id": "email",
            "isDisabled": false,
            "verticalAlignment": "CENTER"
        },
        "longitude": {
            "isCellVisible": true,
            "boxShadow": "none",
            "isDerived": false,
            "computedValue": "{{Table1.sanitizedTableData.map((currentRow) => ( currentRow.longitude))}}",
            "textSize": "0.875rem",
            "index": 3,
            "isVisible": true,
            "label": "longitude",
            "columnType": "text",
            "horizontalAlignment": "LEFT",
            "borderRadius": "0px",
            "width": 150,
            "enableFilter": true,
            "enableSort": true,
            "id": "longitude",
            "isDisabled": false,
            "verticalAlignment": "CENTER"
        }
    },
    "key": "hhy1pv5wsv",
    "derivedColumns": {},
    "labelTextSize": "0.875rem",
    "rightColumn": 64,
    "textSize": "0.875rem",
    "widgetId": "uzqwwkeot4",
    "tableData": "{{fetch_users_data.data}}",
    "label": "Data",
    "searchKey": "",
    "parentId": "j8rq9jrpnd",
    "serverSidePaginationEnabled": true,
    "renderMode": "CANVAS",
    "horizontalAlignment": "LEFT",
    "isVisibleSearch": false,
    "isVisiblePagination": true,
    "verticalAlignment": "CENTER"
}